MANIFEST.in
README.txt
setup.py
kirb/__init__.py
kirb.egg-info/PKG-INFO
kirb.egg-info/SOURCES.txt
kirb.egg-info/dependency_links.txt
kirb.egg-info/namespace_packages.txt
kirb.egg-info/requires.txt
kirb.egg-info/top_level.txt