Metadata-Version: 1.0
Name: kirb
Version: 1.6.1
Summary: Continuous Integration & ReBuild
Home-page: https://github.com/hbmartin/kirb
Author: Harold Martin
Author-email: harold.martin@openx.com
License: BSD
Platform: any
Classifier: Development Status :: 4 - Beta
Classifier: Environment :: Console
Classifier: Environment :: Web Environment
Classifier: Intended Audience :: Developers
Classifier: License :: OSI Approved :: BSD License
Classifier: Operating System :: OS Independent
Classifier: Programming Language :: Python
Classifier: Topic :: Documentation
Classifier: Topic :: Utilities
